{"name":"Haarp-ext-js-viewer","tagline":"A viewer made ​​in Ext Js for HaarpCache","body":"haarp-ext-js-viewer\r\n===================\r\n\r\nA viewer made ​​in Ext Js for HaarpCache\r\n\r\n\r\nInstallation\r\n===================\r\n\r\nNeed to install ExtJs and LibCGI\r\n\r\nFor ExtJs:\r\n\r\n\t#installing unzip\r\n\tapt-get install unzip\r\n\tcd /var/www/\r\n\twget http://extjs.cachefly.net/ext-3.4.0.zip \r\n\tunzip  ext-3.4.0.zip\r\n\tln -s ext-3.4.0 ext\r\n\r\nFor LibCGI:\r\n\r\n\tcd /usr/src\r\n\t#install autoconf\r\n\t#for derivatives debian:\r\n\tapt-get install autoconf\r\n\tgit clone git://github.com/keikurono/libcgi.git\r\n\tcd libcgi\r\n\t./autogen.sh\r\n\t./configure --prefix=/usr\r\n\tmake\r\n\tmake install\t\r\n\r\nInstall HaarpViewer:\r\n\r\n\tcd /usr/src/\r\n\tgit clone git://github.com/keikurono/haarp-ext-js-viewer.git\r\n\tcd haarp-ext-js-viewer\r\n\tcd src/\r\n\tmake\r\n\r\n\tcd ..\r\n\tcp src/*.cgi /usr/lib/cgi-bin/\r\n\tcp hc.html /usr/lib/cgi-bin/\r\n\tcp -r images /var/www/\r\n\ttouch /var/log/haarp/webaccess.log\r\n\tchown www-data:www-data /var/log/haarp/webaccess.log\r\n\techo \"ACCESSWEBLOG /var/log/haarp/webaccess.log\" >> /etc/haarp/haarp.conf\r\n\r\nAccess:\r\n\t\r\n\thttp://<ip_server>/cgi-bin/haarp.cgi\r\n\r\n\r\n![Hviewer](http://img832.imageshack.us/img832/2582/pantallazo1jl.png)\r\n\r\nIf you find this code useful, or wish to fund further development,\r\nyou can use PayPal to donate to the Haarp-Ext-Js-Viewer project:\r\n\r\n<a href=\"https://www.paypal.com/cgi-bin/webscr?cmd=_s-xclick&amp;hosted_button_id=QYCCSYYGW52QU\"><br>\r\n<img src=\"https://www.paypalobjects.com/en_US/i/btn/btn_donateCC_LG.gif\"></a>\r\n","google":"","note":"Don't delete this file! It's used internally to help with page regeneration."}